nx_work_log/SysTrayPaused.ico
nx_work_log/SysTrayRunning.ico
nx_work_log/__init__.py
nx_work_log/change_time_dialog.py
nx_work_log/minute_timer.py
nx_work_log/nx_work_log.rc
nx_work_log/resource.h
nx_work_log/sys_tray_icon.py
nx_work_log/version.py
nx_work_log/win_app.py
nx_work_log-1.1.1.dist-info/LICENSE.txt
nx_work_log-1.1.1.dist-info/METADATA
nx_work_log-1.1.1.dist-info/WHEEL
nx_work_log-1.1.1.dist-info/entry_points.txt
nx_work_log-1.1.1.dist-info/top_level.txt
nx_work_log-1.1.1.dist-info/RECORD
