Metadata-Version: 2.1
Name: nx-work-log
Version: 1.1.1
Summary: NX Solutions Work Log
Author-email: Xander Hendriks <xander@nx-solutions.com>
License: Copyright (c) 2020 NX Solutions
Project-URL: Documentation, https://xanderhendriks.github.io/nx-work-log
Project-URL: Issues, https://github.com/xanderhendriks/nx-work-log/issues
Project-URL: Repository, https://github.com/xanderhendriks/nx-work-log
Classifier: Programming Language :: Python :: 3
Classifier: License :: OSI Approved :: MIT License
Classifier: Operating System :: Microsoft :: Windows
Classifier: Programming Language :: Python :: 3 :: Only
Requires-Python: >=3.7
License-File: LICENSE.txt
Requires-Dist: pywin32 ; platform_system == "Windows"
Provides-Extra: dev
Requires-Dist: wheel ; extra == 'dev'
Requires-Dist: check-manifest ; extra == 'dev'
Requires-Dist: flake8 ; extra == 'dev'
Provides-Extra: doc
Requires-Dist: sphinx ; extra == 'doc'
Requires-Dist: sphinx-rtd-theme ; extra == 'doc'
Provides-Extra: test
Requires-Dist: pytest ; extra == 'test'
